webbote
