Metadata-Version: 2.1
Name: webbote
Version: 3.0
Summary: 用tcp命令驱动ai-bot，控制浏览器
Author: lixin
Author-email: 951163006@qq.com
Keywords: webbote
Classifier: Operating System :: OS Independent
Classifier: Intended Audience :: Developers
Classifier: License :: OSI Approved :: MIT License
Requires-Python: >=3.0
License-File: LICENSE
